clock/__init__.py
clock/main.py
clock/utils.py
clock/commands/__init__.py
clock/commands/command_in.py
clock/local_db/LocalDatabase.py
clock/local_db/__init__.py
cloxz_cli-0.4.0.dist-info/METADATA
cloxz_cli-0.4.0.dist-info/WHEEL
cloxz_cli-0.4.0.dist-info/entry_points.txt
cloxz_cli-0.4.0.dist-info/top_level.txt
cloxz_cli-0.4.0.dist-info/RECORD
