Metadata-Version: 2.1
Name: cloxz-cli
Version: 0.4.0
Requires-Dist: typer
